newsworthy_slides/__init__.py
newsworthy_slides/main.py
newsworthy_slides/parsers.py
newsworthy_slides/utils.py
newsworthy_slides/validationerror.py
newsworthy_slides-1.8.0.dist-info/LICENSE.txt
newsworthy_slides-1.8.0.dist-info/METADATA
newsworthy_slides-1.8.0.dist-info/WHEEL
newsworthy_slides-1.8.0.dist-info/top_level.txt
newsworthy_slides-1.8.0.dist-info/RECORD
