Metadata-Version: 2.1
Name: newsworthy-slides
Version: 1.8.0
Summary: Generate PPTX slides and presentations from HTML markup.
Home-page: https://gitlab.com/newsworthy/newsworthy_slides
Download-URL: https://gitlab.com/newsworthy/newsworthy_slides/archive/1.8.0.tar.gz
Author: Journalism Robotics Stockholm
Author-email: contact@newsworthy.se
License: MIT
Requires-Python: ~=3.5
License-File: LICENSE.txt
Requires-Dist: python-pptx>=0.6.18
Requires-Dist: pytest>=3.10.1
Requires-Dist: beautifulsoup4>=4.7.1
Requires-Dist: requests>=2.22.0
